a9s/__init__.py
a9s/aws_resources/__init__.py
a9s/aws_resources/base_service.py
a9s/aws_resources/dynamodb.py
a9s/aws_resources/help.py
a9s/aws_resources/hud.py
a9s/aws_resources/loader.py
a9s/aws_resources/logo.py
a9s/aws_resources/route53.py
a9s/aws_resources/s3.py
a9s/aws_resources/services.py
a9s/aws_resources/utils.py
a9s/components/__init__.py
a9s/components/app.py
a9s/components/autocomplete.py
a9s/components/custom_string.py
a9s/components/keys.py
a9s/components/logger.py
a9s/components/mode.py
a9s/components/renderer.py
a9s/components/table.py
a9s/components/utils.py
a9s/main.py
a9s/version_file.py
a9s-0.7.0.dist-info/entry_points.txt
a9s-0.7.0.dist-info/WHEEL
a9s-0.7.0.dist-info/METADATA
a9s-0.7.0.dist-info/RECORD
