Metadata-Version: 2.1
Name: a9s
Version: 0.7.0
Summary: Cli tool for navigation in Amazon AWS services. Highly inspired from k9s
Home-page: https://github.com/IamShobe/a9s
License: MIT
Author: Elran Shefer
Author-email: elran777@gmail.com
Requires-Python: >=3.9,<4.0
Classifier: Environment :: Console :: Curses
Classifier: License :: OSI Approved :: MIT License
Classifier: Programming Language :: Python :: 3
Classifier: Programming Language :: Python :: 3 :: Only
Classifier: Programming Language :: Python :: 3.9
Classifier: Topic :: Utilities
Requires-Dist: attrdict (>=2.0.1,<3.0.0)
Requires-Dist: blessed (>=1.18.0,<2.0.0)
Requires-Dist: boto3 (>=1.17.87,<2.0.0)
Requires-Dist: cached-property (>=1.5.2,<2.0.0)
Requires-Dist: colored (>=1.4.2,<2.0.0)
Requires-Dist: pydash (>=5.0.2,<6.0.0)
Requires-Dist: pyperclip (>=1.8.2,<2.0.0)
